sam_anomaly_detector/__init__.py
sam_anomaly_detector/detector.py
sam_anomaly_detector-2.3.dist-info/DESCRIPTION.rst
sam_anomaly_detector-2.3.dist-info/METADATA
sam_anomaly_detector-2.3.dist-info/RECORD
sam_anomaly_detector-2.3.dist-info/WHEEL
sam_anomaly_detector-2.3.dist-info/metadata.json
sam_anomaly_detector-2.3.dist-info/top_level.txt
