Metadata-Version: 2.0
Name: sam-anomaly-detector
Version: 2.3
Summary: Sam media anomaly detector library
Home-page: https://pypi.python.org/pypi/sam-anomaly-detector
Author: Hossein Jazayeri
Author-email: hossein@sam-media.com
License: Apache-2.0
Keywords: forecast,fbprophet,anomaly-detection
Platform: UNKNOWN
Classifier: Programming Language :: Python :: 3
Classifier: Intended Audience :: Developers
Classifier: Operating System :: OS Independent
Classifier: Topic :: Software Development :: Libraries :: Python Modules
Requires-Python: >=3
Requires-Dist: fbprophet
Requires-Dist: numpy
Requires-Dist: pandas
Requires-Dist: pystan
